stormedgesto/__init__.py
stormedgesto/justtest123/__init__.py
stormedgesto/liudi123455/__init__.py
stormedgesto/liudi123455/pp.py
stormedgesto-3.0.0.dist-info/WHEEL
stormedgesto-3.0.0.dist-info/METADATA
stormedgesto-3.0.0.dist-info/RECORD
