Metadata-Version: 2.3
Name: stormedgesto
Version: 3.0.0
Summary: hahahhahh
Author-email: liudi <test@qq.com>
Requires-Dist: gmssl
